xmcp_server_outlook/__init__.py
xmcp_server_outlook/__main__.py
xmcp_server_outlook/server.py
xmcp_server_outlook-0.1.1.dist-info/METADATA
xmcp_server_outlook-0.1.1.dist-info/WHEEL
xmcp_server_outlook-0.1.1.dist-info/entry_points.txt
xmcp_server_outlook-0.1.1.dist-info/RECORD
