Metadata-Version: 2.4
Name: xmcp-server-outlook
Version: 0.1.1
Summary: Outlook操作MCP。主要是发邮箱和操作日历。
Requires-Python: >=3.10
Requires-Dist: flask>=3.1.1
Requires-Dist: mcp[cli]>=1.9.4
Requires-Dist: pywin32>=310
